fastredis/__init__.py
fastredis/basic.py
fastredis/fastredis.py
fastredis-0.1.2.dist-info/METADATA
fastredis-0.1.2.dist-info/WHEEL
fastredis-0.1.2.dist-info/top_level.txt
fastredis-0.1.2.dist-info/RECORD
