Metadata-Version: 2.4
Name: fastredis
Version: 0.1.2
Summary: make it easy to use redis
Home-page: https://gitee.com/ZeroSeeker/fastredis
Author: ZeroSeeker
Author-email: zeroseeker@foxmail.com
Classifier: Programming Language :: Python :: 3
Classifier: License :: OSI Approved :: MIT License
Classifier: Operating System :: OS Independent
Requires-Dist: envx>=1.0.1
Requires-Dist: redis>=4.1.0
Requires-Dist: showlog>=0.0.6
Dynamic: author
Dynamic: author-email
Dynamic: classifier
Dynamic: home-page
Dynamic: requires-dist
Dynamic: summary
